README.txt
setup.py
molnctrl/__init__.py
molnctrl/apisigner.py
molnctrl/cachemaker.py
molnctrl/config.py
molnctrl/connection.py
molnctrl/csexceptions.py
molnctrl/csobjects.py
molnctrl.egg-info/PKG-INFO
molnctrl.egg-info/SOURCES.txt
molnctrl.egg-info/dependency_links.txt
molnctrl.egg-info/requires.txt
molnctrl.egg-info/top_level.txt