Metadata-Version: 1.1
Name: molnctrl
Version: 0.6.0
Summary: A simple python Apache Cloudstack API
Home-page: http://github.com/redbridge/molnctrl
Author: Magnus Bengtsson
Author-email: magnus.bengtsson@redbridge.se
License: UNKNOWN
Platform: UNKNOWN
Classifier: Development Status :: 3 - Alpha
Classifier: Environment :: Console
Classifier: Environment :: Other Environment
Classifier: Intended Audience :: Developers
Classifier: Intended Audience :: System Administrators
Classifier: License :: OSI Approved :: Apache Software License
Classifier: Operating System :: MacOS :: MacOS X
Classifier: Operating System :: Microsoft :: Windows
Classifier: Operating System :: POSIX
Classifier: Programming Language :: Python
Classifier: Topic :: Software Development :: Libraries :: Python Modules
